README
setup.py
mossh/__init__.py
mossh.egg-info/PKG-INFO
mossh.egg-info/SOURCES.txt
mossh.egg-info/dependency_links.txt
mossh.egg-info/entry_points.txt
mossh.egg-info/not-zip-safe
mossh.egg-info/requires.txt
mossh.egg-info/top_level.txt