Metadata-Version: 1.0
Name: mossh
Version: 0.0.3
Summary: An easier way to ssh into your chef servers
Home-page: http://github.com/mopub/mossh
Author: Rob McQueen
Author-email: rob@systemizer.me
License: Apache 2.0
Platform: UNKNOWN
Classifier: Development Status :: 3 - Alpha
Classifier: License :: OSI Approved :: Apache Software License
Classifier: Natural Language :: English
Classifier: Operating System :: OS Independent
Classifier: Programming Language :: Python
